{
  "first_question" : "1",
  "timed" : false,
  "scored" : false,
  "printer": "screen, [TODO]",
  "<ID>" : {
    "question" : {
      "viewable_text" : "What is your name?",
      "next_question" : "<NEXT_QUESTION_ID>", # Null is disabled and -1 lets you end the quest without submitting
      "previous_question" : "<PREV_QUESTION_ID>", # Null is disabled
      "type": "multiple_choice"
    },
    "answers" : [
      {
        "viewable_text" : "John"
      },
      {
        "viewable_text" : "Bob",
        "value" : 2
      },
      {
        "viewable_text" : "Fred",
        "value" : 2,
        "validator" : {

        }
      }
    ]
  },
  "<ID2>" : {}
}