[
  {
    "question": "Player has the ability to purchase a property. What would you like to do?",
        "answers": [
          {
            "answer" : "Purchase a Property.",
            "value" : 0
          },
          {
            "answer" : "Sell the ability to purchase a property.",
            "value" : 1
          },
          {
            "answer" : "Do nothing / Burn the ability to purchase a property.",
            "value" : -2
          }
        ],
    "sub-questions" : [
      {
        "question": "Which property would you like to buy?",
        "answers": [
          "Blue",
          "Black",
          "Red",
          "White"
        ]
      },
      {
       "question": "How much would you like to sell the property for?",
        "answers": {
          "math_validation": "<answer> % 500 == 0",
          "error" : "Answer must be divisible by 500."
        }
      }
    ]
  }
]